uengineer/__init__.py
uengineer/dataset.py
uengineer/modelpyfe3d.py
uengineer/models.py
uengineer/version.py
uengineer/data/__init__.py
uengineer/data/pCRM9_wing/README.md
uengineer/data/pCRM9_wing/__init__.py
uengineer/data/pCRM9_wing/pCRM9_103_MAIN_FILE.bdf
uengineer/data/pCRM9_wing/pCRM9_CONM2_MTOW.dat
uengineer/data/pCRM9_wing/pCRM9_PSHELL.dat
uengineer/data/pCRM9_wing/pCRM9_mat.dat
uengineer/data/pCRM9_wing/pCRM9_model_2.dat
uengineer/data/pCRM9_wing/pCRM9_ribs_fem.dat
uengineer-0.1.8.data/data/AUTHORS
uengineer-0.1.8.data/data/LICENSE
uengineer-0.1.8.data/data/README.md
uengineer-0.1.8.dist-info/AUTHORS
uengineer-0.1.8.dist-info/LICENSE
uengineer-0.1.8.dist-info/METADATA
uengineer-0.1.8.dist-info/WHEEL
uengineer-0.1.8.dist-info/top_level.txt
uengineer-0.1.8.dist-info/RECORD
