Metadata-Version: 2.1
Name: uengineer
Version: 0.1.8
Summary: Modules used by the UEngineer Community courses
Home-page: https://github.com/saullocastro/uengineer
Author: Saullo G. P. Castro, Vinicius L. Lemos
Author-email: s.g.p.castro@gmail.com
License: 3-Clause BSD
Keywords: finite elements structural analysis static buckling vibration dynamics
Platform: UNKNOWN
Classifier: Development Status :: 3 - Alpha
Classifier: Intended Audience :: Education
Classifier: Intended Audience :: Science/Research
Classifier: Intended Audience :: Developers
Classifier: Topic :: Scientific/Engineering :: Mathematics
Classifier: Topic :: Education
Classifier: License :: OSI Approved :: BSD License
Classifier: Programming Language :: Python :: 3.7
Classifier: Programming Language :: Python :: 3.8
Classifier: Programming Language :: Python :: 3.9
Classifier: Programming Language :: Python :: 3.10
Classifier: Operating System :: Microsoft :: Windows
Classifier: Operating System :: Unix
License-File: LICENSE
License-File: AUTHORS
Requires-Dist: numpy
Requires-Dist: scipy
Requires-Dist: pynastran
Requires-Dist: pyfe3d
Requires-Dist: requests
Requires-Dist: matplotlib
